informatikunterricht/__init__.py
informatikunterricht/bildverarbeitung.py
informatikunterricht/diagramme.py
informatikunterricht-0.2.4.dist-info/LICENSE.txt
informatikunterricht-0.2.4.dist-info/METADATA
informatikunterricht-0.2.4.dist-info/WHEEL
informatikunterricht-0.2.4.dist-info/top_level.txt
informatikunterricht-0.2.4.dist-info/RECORD
