Metadata-Version: 2.1
Name: informatikunterricht
Version: 0.2.4
Summary: Ein Paket für den Informatikunterricht, das Module zur Bildverarbeitung und Diagrammerstellung enthält.
Home-page: https://github.com/henningmattes/informatikunterricht
Author: Henning Mattes
Author-email: henning_mattes@gmx.de
License: MIT with additional terms
Keywords: bildung informatik bildverarbeitung diagramme informatikunterricht
Classifier: Development Status :: 3 - Alpha
Classifier: Intended Audience :: Education
Classifier: License :: OSI Approved :: MIT License
Classifier: Programming Language :: Python :: 3
Classifier: Programming Language :: Python :: 3.7
Classifier: Programming Language :: Python :: 3.8
Classifier: Programming Language :: Python :: 3.9
Classifier: Topic :: Education
Classifier: Topic :: Software Development :: Libraries :: Python Modules
Requires-Python: >=3.7
License-File: LICENSE.txt
Requires-Dist: matplotlib
Requires-Dist: numpy
Requires-Dist: Pillow
